featureform/__init__.py
featureform/__main__.py
featureform/cli.py
featureform/client.py
featureform/constants.py
featureform/deploy.py
featureform/enums.py
featureform/exceptions.py
featureform/feature_flag.py
featureform/file_utils.py
featureform/format.py
featureform/get.py
featureform/grpc_client.py
featureform/list.py
featureform/logging.py
featureform/parse.py
featureform/register.py
featureform/resources.py
featureform/search.py
featureform/serving.py
featureform/status_display.py
featureform/tls.py
featureform/train_test_split.py
featureform/type_objects.py
featureform/types.py
featureform/variant_names_generator.py
featureform/version.py
featureform/dashboard/out/404.html
featureform/dashboard/out/[type].html
featureform/dashboard/out/favicon.ico
featureform/dashboard/out/index.html
featureform/dashboard/out/query.html
featureform/dashboard/out/robots.txt
featureform/dashboard/out/search.html
featureform/dashboard/out/site.webmanifest
featureform/dashboard/out/tasks.html
featureform/dashboard/out/[type]/[entity].html
featureform/dashboard/out/_next/static/YasT6wJo6Veq5kdKyjvsv/_buildManifest.js
featureform/dashboard/out/_next/static/YasT6wJo6Veq5kdKyjvsv/_ssgManifest.js
featureform/dashboard/out/_next/static/chunks/framework-8c11e478f100ae7f.js
featureform/dashboard/out/_next/static/chunks/framework-8c11e478f100ae7f.js.map
featureform/dashboard/out/_next/static/chunks/main-02179f2391fe9c08.js
featureform/dashboard/out/_next/static/chunks/main-02179f2391fe9c08.js.map
featureform/dashboard/out/_next/static/chunks/polyfills-c67a75d1b6f99dc8.js
featureform/dashboard/out/_next/static/chunks/react-syntax-highlighter_languages_refractor_abap.b919f69339df06c8.js
featureform/dashboard/out/_next/static/chunks/react-syntax-highlighter_languages_refractor_abap.b919f69339df06c8.js.map
featureform/dashboard/out/_next/static/chunks/react-syntax-highlighter_languages_refractor_abnf.8ca3fe19e799e6a8.js
featureform-1.15.8.dist-info/licenses/LICENSE
featureform-1.15.8.dist-info/METADATA
featureform-1.15.8.dist-info/WHEEL
featureform-1.15.8.dist-info/entry_points.txt
featureform-1.15.8.dist-info/top_level.txt
featureform-1.15.8.dist-info/RECORD
