Metadata-Version: 2.4
Name: featureform
Version: 1.15.8
Summary: Package for the Featureform Feature Store
Home-page: https://featureform.com
Author: FeatureForm, Inc.
Author-email: hello@featureform.com
Project-URL: Bug Tracker, https://github.com/featureform/featureform/issues
Classifier: Programming Language :: Python :: 3
Classifier: Operating System :: OS Independent
Requires-Python: >=3.9
License-File: LICENSE
Requires-Dist: click>=7.1.2
Requires-Dist: protobuf>=3.20.0
Requires-Dist: typeguard<3.0.0
Requires-Dist: grpcio>=1.47.0
Requires-Dist: googleapis-common-protos
Requires-Dist: numpy>=1.21.6
Requires-Dist: pandas<2.2.0,>=1.3.5
Requires-Dist: pandasql>=0.7.3
Requires-Dist: typing_extensions>=4.1.1
Requires-Dist: dataclasses==0.6
Requires-Dist: flask>=3.0.0
Requires-Dist: Flask-Cors>=3.0.10
Requires-Dist: validators>=0.20.0
Requires-Dist: dill==0.3.7
Requires-Dist: pandasql==0.7.3
Requires-Dist: sqlalchemy<2.0.0
Requires-Dist: requests
Requires-Dist: rich
Requires-Dist: pyarrow
Requires-Dist: pyyaml
Requires-Dist: fastparquet
Requires-Dist: pinecone-client
Requires-Dist: weaviate-client
Requires-Dist: docker
Requires-Dist: uuid
Requires-Dist: importlib-metadata
Requires-Dist: pyiceberg[glue]
Requires-Dist: astor
Dynamic: license-file
